1603045_verilog_code.v
module assignment
(
    input A, B, C, D, E, F,
    output out
);

wire A_, B_, C_, A_B_, A_B_C_, A_B_C_D, A_B_C_DE, A_B_C_DEF, A_B;

not(A_, A);
not(B_, B);
not(C_, C);

and(A_B_, A_, B_);
and(A_B_C_, A_B_, C_);
and(A_B_C_D, A_B_C_, D);
and(A_B_C_DE, A_B_C_D, E);
and(A_B_C_DEF, A_B_C_DE, F);

and(A_B, A_, B);

or(out, A_B_C_DEF, A_B);

endmodule

1603045_stimulus_testbench.v
`timescale 1ns / 1ps
module stimulus;

//inputs
reg A, B, C, D, E, F;

//outputs
wire A_, B_, C_, A_B_, A_B_C_, A_B_C_D, A_B_C_DE, A_B_C_DEF, A_B, out;

assignment uut
(
    .A(A), .B(B), .C(C), .D(D), .E(E), .F(F), .out(out)
);

initial 
begin
    $dumpfile("test.vcd");
    $dumpvars(0, stimulus);
    A = 0; B = 0; C = 0; D = 0; E = 0; F = 0;

    #5
    A = 0; B = 0; C = 0; D = 0; E = 0; F = 1;

    #5
    A = 0; B = 0; C = 0; D = 0; E = 1; F = 0;

    #5
    A = 0; B = 0; C = 0; D = 0; E = 1; F = 1;
    
    #5
    A = 0; B = 0; C = 0; D = 1; E = 0; F = 0;
    
    #5
    A = 0; B = 1; C = 0; D = 1; E = 0; F = 1;
    
    #5
    A = 1; B = 1; C = 0; D = 0; E = 1; F = 1;
    
    #5
    A = 0; B = 0; C = 1; D = 1; E = 0; F = 0;
    
    #5
    A = 1; B = 1; C = 1; D = 0; E = 0; F = 0;
    
    #5
    A = 1; B = 1; C = 1; D = 1; E = 1; F = 1;

end

initial 
begin
    $monitor("A=%d, B=%d, C=%d, D=%d, E=%d, F=%d, Ouput=%d \n", A, B, C, D, E, F, out);
end

endmodule

test.vcd
$date
	Sun Nov 29 01:00:36 2020
$end
$version
	Icarus Verilog
$end
$timescale
	1ps
$end
$scope module stimulus $end
$var wire 1 ! out $end
$var reg 1 " A $end
$var reg 1 # B $end
$var reg 1 $ C $end
$var reg 1 % D $end
$var reg 1 & E $end
$var reg 1 ' F $end
$scope module uut $end
$var wire 1 " A $end
$var wire 1 ( A_ $end
$var wire 1 ) A_B $end
$var wire 1 * A_B_ $end
$var wire 1 + A_B_C_ $end
$var wire 1 , A_B_C_D $end
$var wire 1 - A_B_C_DE $end
$var wire 1 . A_B_C_DEF $end
$var wire 1 # B $end
$var wire 1 / B_ $end
$var wire 1 $ C $end
$var wire 1 0 C_ $end
$var wire 1 % D $end
$var wire 1 & E $end
$var wire 1 ' F $end
$var wire 1 ! out $end
$upscope $end
$upscope $end
$enddefinitions $end
#0
$dumpvars
10
1/
0.
0-
0,
1+
1*
0)
1(
0'
0&
0%
0$
0#
0"
0!
$end
#5000
1'
#10000
0'
1&
#15000
1'
#20000
1,
0'
0&
1%
#25000
0,
0+
0*
1!
0/
1)
1'
1#
#30000
0!
0)
0(
1&
0%
1"
#35000
1*
00
1/
1(
0'
0&
1%
1$
0#
0"
#40000
0*
0/
0(
0%
1#
1"
#45000
1'
1&
1%
